CHANGELOG.rst
LICENSE
MANIFEST.in
README.rst
setup.py
absolute/__init__.py
absolute/context_processors.py
absolute/models.py
absolute/settings.py
absolute/tests.py
absolute/urls.py
absolute/wsgi.py
absolute/templatetags/__init__.py
absolute/templatetags/absolute.py
absolute/templatetags/absolute_future.py
django_absolute.egg-info/PKG-INFO
django_absolute.egg-info/SOURCES.txt
django_absolute.egg-info/dependency_links.txt
django_absolute.egg-info/requires.txt
django_absolute.egg-info/top_level.txt