Metadata-Version: 1.1
Name: django-absolute
Version: 0.3
Summary: Absolute URLs tools for django
Home-page: https://github.com/noirbizarre/django-absolute
Author: Axel Haustant
Author-email: noirbizarre+absolute@gmail.com
License: LGPL
Download-URL: http://pypi.python.org/pypi/django-absolute
Platform: UNKNOWN
Classifier: Framework :: Django
Classifier: Development Status :: 4 - Beta
Classifier: Programming Language :: Python
Classifier: Environment :: Web Environment
Classifier: Operating System :: OS Independent
Classifier: Intended Audience :: Developers
Classifier: Topic :: System :: Software Distribution
Classifier: Programming Language :: Python
Classifier: Topic :: Software Development :: Libraries :: Python Modules
Classifier: License :: OSI Approved :: GNU Library or Lesser General Public License (LGPL)
